httplint/__init__.py
httplint/cache.py
httplint/content_encoding.py
httplint/content_type.py
httplint/i18n.py
httplint/message.py
httplint/note.py
httplint/py.typed
httplint/status.py
httplint/types.py
httplint/util.py
httplint/cli/__init__.py
httplint/cli/http_parser.py
httplint/field/__init__.py
httplint/field/broken_field.py
httplint/field/cors.py
httplint/field/deprecated.py
httplint/field/description.py
httplint/field/finder.py
httplint/field/json_field.py
httplint/field/list_field.py
httplint/field/section.py
httplint/field/singleton_field.py
httplint/field/structured_field.py
httplint/field/tests.py
httplint/field/unnecessary.py
httplint/field/utils.py
httplint/field/parsers/__init__.py
httplint/field/parsers/accept.py
httplint/field/parsers/accept_ch.py
httplint/field/parsers/accept_encoding.py
httplint/field/parsers/accept_language.py
httplint/field/parsers/accept_ranges.py
httplint/field/parsers/access_control.py
httplint/field/parsers/access_control_allow_credentials.py
httplint/field/parsers/access_control_allow_headers.py
httplint/field/parsers/access_control_allow_methods.py
httplint/field/parsers/access_control_allow_origin.py
httplint/field/parsers/access_control_expose_headers.py
httplint/field/parsers/access_control_max_age.py
httplint/field/parsers/access_control_request_headers.py
httplint/field/parsers/access_control_request_method.py
httplint/field/parsers/age.py
httplint/field/parsers/allow.py
httplint/field/parsers/alt_svc.py
httplint/field/parsers/authentication_info.py
httplint/field/parsers/authorization.py
httplint/field/parsers/available_dictionary.py
httplint/field/parsers/cache_control.py
httplint/field/parsers/cache_group_invalidation.py
httplint/field/parsers/cache_groups.py
httplint/field/parsers/cache_status.py
httplint/field/parsers/cdn_cache_control.py
httplint/field/parsers/clear_site_data.py
httplint/field/parsers/connection.py
httplint/field/parsers/connectiox.py
httplint/field/parsers/content_base.py
httplint-2026.2.2.dist-info/licenses/LICENSE.md
httplint-2026.2.2.dist-info/METADATA
httplint-2026.2.2.dist-info/WHEEL
httplint-2026.2.2.dist-info/entry_points.txt
httplint-2026.2.2.dist-info/top_level.txt
httplint-2026.2.2.dist-info/RECORD
