Metadata-Version: 2.4
Name: httplint
Version: 2026.2.2
Summary: Lint for HTTP messages.
Author-email: Mark Nottingham <mnot@mnot.net>
License: Copyright (c) Mark Nottingham
Project-URL: homepage, https://github.com/mnot/httplint/
Classifier: Operating System :: OS Independent
Classifier: Development Status :: 4 - Beta
Classifier: License :: OSI Approved :: MIT License
Classifier: Intended Audience :: Developers
Classifier: Intended Audience :: System Administrators
Classifier: Topic :: Internet :: WWW/HTTP
Classifier: Topic :: Software Development :: Testing
Requires-Python: >=3.10
License-File: LICENSE.md
Requires-Dist: Markdown
Requires-Dist: MarkupSafe
Requires-Dist: thor
Requires-Dist: typing_extensions
Requires-Dist: http-sf>=1.1.1
Requires-Dist: sniffpy==1.0.0
Requires-Dist: Babel
Requires-Dist: Brotli
Provides-Extra: dev
Requires-Dist: mypy; extra == "dev"
Requires-Dist: black; extra == "dev"
Requires-Dist: pylint; extra == "dev"
Requires-Dist: pytest; extra == "dev"
Requires-Dist: pytest-md; extra == "dev"
Requires-Dist: validate-pyproject; extra == "dev"
Requires-Dist: build; extra == "dev"
Requires-Dist: twine; extra == "dev"
Requires-Dist: types-Markdown; extra == "dev"
Requires-Dist: llm; extra == "dev"
Requires-Dist: llm-mlx; extra == "dev"
Requires-Dist: brotli-stubs; extra == "dev"
Dynamic: license-file
